pytest_platform_adapter/__init__.py
pytest_platform_adapter/plugin.py
pytest_platform_adapter-1.2.0.dist-info/licenses/LICENSE
pytest_platform_adapter-1.2.0.dist-info/METADATA
pytest_platform_adapter-1.2.0.dist-info/WHEEL
pytest_platform_adapter-1.2.0.dist-info/entry_points.txt
pytest_platform_adapter-1.2.0.dist-info/top_level.txt
pytest_platform_adapter-1.2.0.dist-info/RECORD
