Metadata-Version: 2.4
Name: pytest_platform_adapter
Version: 1.2.0
Summary: Pytest集成自动化平台插件
Author-email: BlackYau <blackyau426@gmail.com>
Maintainer-email: BlackYau <blackyau426@gmail.com>
License: MIT
Project-URL: Homepage, https://github.com/blackyau/pytest-platform-adapter
Project-URL: Repository, https://github.com/blackyau/pytest-platform-adapter.git
Project-URL: Issues, https://github.com/blackyau/pytest-platform-adapter/issues
Keywords: pytest,platform,adapter,自动化平台,插件
Classifier: Development Status :: 5 - Production/Stable
Classifier: Environment :: Plugins
Classifier: Framework :: Pytest
Classifier: Intended Audience :: Developers
Classifier: License :: OSI Approved :: MIT License
Classifier: Natural Language :: Chinese (Simplified)
Classifier: Programming Language :: Python :: 3
Classifier: Programming Language :: Python :: 3.6
Classifier: Programming Language :: Python :: 3.7
Classifier: Programming Language :: Python :: 3.8
Classifier: Programming Language :: Python :: 3.9
Classifier: Programming Language :: Python :: 3.10
Classifier: Programming Language :: Python :: 3.11
Classifier: Topic :: Software Development
Classifier: Topic :: Software Development :: Testing
Classifier: Topic :: Software Development :: Testing :: Acceptance
Classifier: Topic :: Software Development :: Libraries
Classifier: Topic :: Software Development :: Libraries :: Python Modules
Requires-Python: >=3.6
License-File: LICENSE
Requires-Dist: pytest>=6.2.5
Requires-Dist: allure-pytest>=2.9.45
Dynamic: license-file
